ethernity_cloud_sdk_py/__init__.py
ethernity_cloud_sdk_py/cli.py
ethernity_cloud_sdk_py/commands/__init__.py
ethernity_cloud_sdk_py/commands/build.py
ethernity_cloud_sdk_py/commands/init.py
ethernity_cloud_sdk_py/commands/publish.py
ethernity_cloud_sdk_py/commands/.mypy_cache/.gitignore
ethernity_cloud_sdk_py/commands/.mypy_cache/CACHEDIR.TAG
ethernity_cloud_sdk_py/commands/.mypy_cache/3.10/@plugins_snapshot.json
ethernity_cloud_sdk_py/commands/.mypy_cache/3.10/_ast.data.json
ethernity_cloud_sdk_py/commands/.mypy_cache/3.10/_ast.meta.json
ethernity_cloud_sdk_py/commands/.mypy_cache/3.10/_codecs.data.json
ethernity_cloud_sdk_py/commands/.mypy_cache/3.10/_codecs.meta.json
ethernity_cloud_sdk_py/commands/.mypy_cache/3.10/_collections_abc.data.json
ethernity_cloud_sdk_py/commands/.mypy_cache/3.10/_collections_abc.meta.json
ethernity_cloud_sdk_py/commands/.mypy_cache/3.10/_compression.data.json
ethernity_cloud_sdk_py/commands/.mypy_cache/3.10/_compression.meta.json
ethernity_cloud_sdk_py/commands/.mypy_cache/3.10/abc.data.json
ethernity_cloud_sdk_py/commands/.mypy_cache/3.10/abc.meta.json
ethernity_cloud_sdk_py/commands/.mypy_cache/3.10/builtins.data.json
ethernity_cloud_sdk_py/commands/.mypy_cache/3.10/builtins.meta.json
ethernity_cloud_sdk_py/commands/.mypy_cache/3.10/bz2.data.json
ethernity_cloud_sdk_py/commands/.mypy_cache/3.10/bz2.meta.json
ethernity_cloud_sdk_py/commands/.mypy_cache/3.10/codecs.data.json
ethernity_cloud_sdk_py/commands/.mypy_cache/3.10/codecs.meta.json
ethernity_cloud_sdk_py/commands/.mypy_cache/3.10/contextlib.data.json
ethernity_cloud_sdk_py/commands/.mypy_cache/3.10/contextlib.meta.json
ethernity_cloud_sdk_py/commands/.mypy_cache/3.10/dataclasses.data.json
ethernity_cloud_sdk_py/commands/.mypy_cache/3.10/dataclasses.meta.json
ethernity_cloud_sdk_py/commands/.mypy_cache/3.10/enum.data.json
ethernity_cloud_sdk_py/commands/.mypy_cache/3.10/enum.meta.json
ethernity_cloud_sdk_py/commands/.mypy_cache/3.10/genericpath.data.json
etny_cloud_sdk_py-0.1.31.dist-info/LICENSE
etny_cloud_sdk_py-0.1.31.dist-info/METADATA
etny_cloud_sdk_py-0.1.31.dist-info/WHEEL
etny_cloud_sdk_py-0.1.31.dist-info/entry_points.txt
etny_cloud_sdk_py-0.1.31.dist-info/top_level.txt
etny_cloud_sdk_py-0.1.31.dist-info/RECORD
